{
  "title": "Senior Backend Engineer",
  "level": "Senior",
  "responsibilities": "Not specified",
  "kpis": "Not specified",
  "skills": "FastAPI, MongoDB",
  "relevant_experience": 0,
  "total_experience": 0,
  "compensation_range": "Not specified",
  "work_structure": "In-office, Hybrid, or Remote (no specific preference mentioned)",
  "location": "",
  "hiring_timeline": "Not specified",
  "urgency": "Not specified",
  "num_positions": 1,
  "gender_preference": "Any",
  "college_preference": "",
  "college_exclusion": ""
}